edx_prefectutils/__init__.py
edx_prefectutils/bigquery.py
edx_prefectutils/common.py
edx_prefectutils/edx_api_client.py
edx_prefectutils/email_unsubscribes.py
edx_prefectutils/hubspot_leads.py
edx_prefectutils/mysql.py
edx_prefectutils/paypal.py
edx_prefectutils/paypal_xml.py
edx_prefectutils/record.py
edx_prefectutils/s3.py
edx_prefectutils/sitemap.py
edx_prefectutils/snowflake.py
edx_prefectutils/vault_secrets.py
edx_prefectutils-2.4.4.dist-info/AUTHORS.rst
edx_prefectutils-2.4.4.dist-info/LICENSE.txt
edx_prefectutils-2.4.4.dist-info/METADATA
edx_prefectutils-2.4.4.dist-info/WHEEL
edx_prefectutils-2.4.4.dist-info/entry_points.txt
edx_prefectutils-2.4.4.dist-info/top_level.txt
edx_prefectutils-2.4.4.dist-info/RECORD
