Metadata-Version: 2.1
Name: edx-prefectutils
Version: 2.4.4
Summary: Utility code to assist in writing Prefect Flows.
Home-page: https://github.com/edx/edx-prefectutils
Author: Julia Eskew
Author-email: jeskew@edx.org
License: AGPL
Keywords: edx_prefectutils
Classifier: Development Status :: 2 - Pre-Alpha
Classifier: Intended Audience :: Developers
Classifier: Natural Language :: English
Classifier: License :: OSI Approved :: GNU Affero General Public License v3
Classifier: Programming Language :: Python :: 3
Classifier: Programming Language :: Python :: 3.8
Requires-Python: >=3.8
License-File: LICENSE.txt
License-File: AUTHORS.rst
Requires-Dist: paramiko
Requires-Dist: hvac
Requires-Dist: mysql-connector-python (==8.0.21)
Requires-Dist: importlib-metadata (==8.4.0)
Requires-Dist: backoff
Requires-Dist: edx-opaque-keys
Requires-Dist: prefect[aws,google,snowflake,viz] (==1.4.1)
Requires-Dist: boto3
Requires-Dist: ciso8601
Requires-Dist: botocore
